{
  "ComponentIndexes": {},
  "ControlUniqueGuids": {},
  "ControlUniqueIds": {
    "App": 1,
    "ArchivosPdf": 172,
    "ArchivosPdfSinSalario": 225,
    "Button1": 58,
    "Button1_1": 51,
    "Button1_2": 47,
    "Button1_3": 32,
    "Button2": 198,
    "Button2_1": 199,
    "Button2_2": 253,
    "Button2_3": 250,
    "Button2_4": 168,
    "Button2_5": 169,
    "Button2_6": 79,
    "Button2_7": 80,
    "Button3": 173,
    "Button3_1": 226,
    "Button3_2": 144,
    "Button3_3": 61,
    "Button3_4": 84,
    "Button5": 23,
    "CheckboxSalario": 50,
    "colilla": 262,
    "ColillaPago": 83,
    "ComboBox1": 55,
    "ComboBox1_1": 57,
    "Container11": 263,
    "Container13": 272,
    "Container13_1": 273,
    "Container13_2": 288,
    "Container13_3": 293,
    "Container13_4": 314,
    "Container13_5": 320,
    "Container15": 275,
    "Container17": 317,
    "Container2": 14,
    "Container3": 7,
    "Container4": 8,
    "Container5": 9,
    "Container6": 12,
    "Container7": 42,
    "Container7_1": 38,
    "Container8": 15,
    "containerCartaLaboral": 48,
    "containerColillas": 52,
    "ContainerFormularios": 20,
    "containerPermiso": 33,
    "containerVacaciones": 24,
    "DatePicker4_1": 29,
    "DatePicker4_2": 30,
    "DatePickerPermiso": 41,
    "Gallery3": 21,
    "galleryTemplate3": 22,
    "HeaderContainer1": 6,
    "horaInicialPermiso": 43,
    "horaPermisoFinal": 39,
    "Host": 3,
    "Image1": 174,
    "Image1_1": 227,
    "Image1_2": 143,
    "Image1_3": 60,
    "Image10": 264,
    "Image11": 319,
    "Image7": 17,
    "Image8": 18,
    "Image9": 13,
    "Label1": 53,
    "Label10": 31,
    "Label11": 179,
    "Label11_10": 66,
    "Label11_11": 67,
    "Label11_3": 181,
    "Label11_4": 232,
    "Label11_5": 234,
    "Label11_6": 236,
    "Label11_7": 237,
    "Label11_8": 149,
    "Label11_9": 150,
    "Label12": 26,
    "Label12_1": 28,
    "Label12_2": 27,
    "Label13": 186,
    "Label13_1": 184,
    "Label13_10": 239,
    "Label13_11": 240,
    "Label13_12": 242,
    "Label13_13": 244,
    "Label13_14": 247,
    "Label13_15": 249,
    "Label13_16": 153,
    "Label13_17": 251,
    "Label13_18": 254,
    "Label13_19": 255,
    "Label13_2": 188,
    "Label13_20": 196,
    "Label13_21": 159,
    "Label13_22": 167,
    "Label13_23": 70,
    "Label13_24": 72,
    "Label13_26": 78,
    "Label13_27": 74,
    "Label13_28": 162,
    "Label13_29": 163,
    "Label13_3": 190,
    "Label13_30": 155,
    "Label13_31": 166,
    "Label13_32": 158,
    "Label13_33": 161,
    "Label13_34": 75,
    "Label13_4": 189,
    "Label13_5": 193,
    "Label13_6": 197,
    "Label13_7": 200,
    "Label13_8": 202,
    "Label13_9": 203,
    "Label14": 183,
    "Label14_1": 191,
    "Label14_10": 82,
    "Label14_12": 157,
    "Label14_13": 164,
    "Label14_14": 154,
    "Label14_15": 170,
    "Label14_17": 165,
    "Label14_18": 160,
    "Label14_19": 156,
    "Label14_2": 192,
    "Label14_20": 73,
    "Label14_22": 76,
    "Label14_25": 81,
    "Label14_3": 194,
    "Label14_4": 238,
    "Label14_5": 245,
    "Label14_6": 246,
    "Label14_7": 248,
    "Label14_9": 171,
    "Label15": 279,
    "Label15_2": 281,
    "Label15_3": 285,
    "Label15_4": 286,
    "Label15_5": 287,
    "Label16": 185,
    "Label16_1": 195,
    "Label16_2": 241,
    "Label17": 177,
    "Label17_1": 230,
    "Label17_2": 146,
    "Label17_3": 63,
    "Label17_4": 77,
    "Label19": 265,
    "Label2": 49,
    "Label23": 266,
    "Label23_1": 270,
    "Label23_2": 268,
    "Label24": 274,
    "Label24_1": 289,
    "Label24_2": 290,
    "Label24_3": 291,
    "Label24_4": 292,
    "Label24_5": 321,
    "Label24_7": 322,
    "Label28": 276,
    "Label28_1": 278,
    "Label28_2": 277,
    "Label28_3": 284,
    "Label28_4": 282,
    "Label28_5": 283,
    "Label3": 34,
    "Label30": 315,
    "Label31": 316,
    "Label32_1": 318,
    "Label4": 16,
    "Label5": 10,
    "Label5_1": 11,
    "Label6": 25,
    "Label7": 54,
    "Label7_1": 56,
    "Label8": 175,
    "Label8_1": 201,
    "Label8_2": 176,
    "Label8_3": 228,
    "Label8_4": 229,
    "Label8_5": 252,
    "Label8_6": 145,
    "Label8_7": 147,
    "Label8_8": 62,
    "Label8_9": 64,
    "Label9": 35,
    "Label9_1": 36,
    "Label9_2": 37,
    "Label9_3": 45,
    "MainSectionContainer1": 19,
    "minutoInicialPermiso": 44,
    "minutoPermisoFinal": 40,
    "pdfPermisos": 142,
    "Rectangle3": 178,
    "Rectangle3_1": 231,
    "Rectangle3_2": 148,
    "Rectangle3_3": 65,
    "Screen2": 4,
    "ScreenContainer1": 5,
    "TextInput1": 182,
    "TextInput1_1": 235,
    "TextInput1_2": 151,
    "TextInput1_3": 180,
    "TextInput1_5": 233,
    "TextInput1_6": 69,
    "TextInput1_7": 68,
    "TextInput2": 280,
    "TextInput3": 187,
    "TextInput3_1": 243,
    "TextInput3_2": 152,
    "TextInput3_3": 71,
    "TextInput4_10": 323,
    "TextInput4_11": 324,
    "TextInput4_12": 325,
    "TextInput4_13": 326,
    "TextInput4_14": 327,
    "TextInput4_15": 328,
    "TextInput4_16": 329,
    "TextInput4_17": 330,
    "TextInput4_18": 331,
    "TextInput4_19": 332,
    "TextInput4_20": 333,
    "TextInput4_21": 334,
    "TextInput4_22": 335,
    "TextInput4_23": 336,
    "TextInput4_24": 337,
    "TextInput4_25": 338,
    "TextInput4_26": 339,
    "TextInput4_27": 340,
    "TextInput4_28": 341,
    "TextInput4_6": 267,
    "TextInput4_7": 269,
    "TextInput4_8": 271,
    "TextInput4_9": 294,
    "TextInputMotivo": 46,
    "Vacaciones": 59
  },
  "FunctionParamsInvariantScripts": {},
  "FunctionParamsInvariantScriptsOnInstances": {},
  "HeaderLastSavedDateTimeUTC": "05/05/2023 16:30:16",
  "IsLegacyComponentAllowGlobalScopeCase": false,
  "LocalConnectionIDReferences": {
    "4d7fcff4-6f5f-45c2-9b25-c6b482d89763": "\"/providers/microsoft.powerapps/apis/shared_office365users/connections/df5c8c2f115f4c4480b2fa5deeec4966\"",
    "66eb3c18-72fa-4ead-ad1a-26a0d6e0b581": "\"/providers/microsoft.powerapps/apis/shared_office365/connections/shared-office365-eb8e6c23-f2a4-413f-9bfc-cb516c7bf868\"",
    "7bf5d151-fd6e-4381-8e09-b734088ca394": "\"/providers/microsoft.powerapps/apis/shared_sharepointonline/connections/d52903572e9642f0a51934a359169b05\"",
    "c157dfae-bd75-49e7-ad5a-1ff7d00aa96f": "\"/providers/microsoft.powerapps/apis/shared_logicflows/connections/21c012a3-a4a5-4a58-87b0-d99bca14fa62\"",
    "c9edfb0c-d5e0-4fb0-b784-597a6d4deb00": "\"/providers/microsoft.powerapps/apis/shared_logicflows/connections/72ce1050-e43a-40d8-83c1-3df2715a0321\"",
    "d581bf5f-31bd-4882-ad3b-6535b5451719": "\"/providers/microsoft.powerapps/apis/shared_sharepointonline/connections/0866981ad3a04377bb1a289b485850c3\""
  },
  "LocalDatabaseReferencesAsEmpty": false,
  "LocalResourceFileNames": {
    "Fondo App": "2f7dd5b7-79b3-43fa-b6bf-2d0ff76f1310.png",
    "Logo 2": "f6789e2e-94dd-42bd-bbed-a1d8ec37010b.png",
    "Logo Final": "6e8e6289-3f7d-43eb-a20d-ad611766561a.png",
    "Logo Final (1)": "512fa82a-f9fe-4aa1-8f10-724d9bc2d14e.png",
    "ruddy": "52a5ea63-50e0-4e1a-a3e1-addb80e9ef1a.jpeg",
    "Walk": "bb1b3623-66e7-42ea-a982-8cda9e09c291.gif"
  },
  "LocalResourceRootPaths": {
    "Fondo App": "https://docserverpwaprodsbr.blob.core.windows.net/c155022b-f0d7-44d3-98db-afdc300dd530-1/resource/Assets0Images02f7dd5b7-79b3-43fa-b6bf-2d0ff76f1310.png?sv=2018-03-28&sr=b&sig=i3M%2B5YQJ5tgbxTGLEcnrgBxCb4ihy9v%2BM%2Bg0cVdikzw%3D&spr=https&se=2023-05-06T16%3A00%3A06Z&sp=r",
    "Logo 2": "https://docserverpwaprodsbr.blob.core.windows.net/c155022b-f0d7-44d3-98db-afdc300dd530-1/resource/Assets0Images0f6789e2e-94dd-42bd-bbed-a1d8ec37010b.png?sv=2018-03-28&sr=b&sig=3aH73u4F%2BCJxRkmcLiSN7mdM3TsJpY4DOtyLRozLABU%3D&spr=https&se=2023-05-06T16%3A00%3A06Z&sp=r",
    "Logo Final": "https://docserverpwaprodsbr.blob.core.windows.net/c155022b-f0d7-44d3-98db-afdc300dd530-1/resource/Assets0Images06e8e6289-3f7d-43eb-a20d-ad611766561a.png?sv=2018-03-28&sr=b&sig=JyuHkVW%2FQi9arbusNBVq9GZVWJmiG9p%2BmYe%2Fc%2BLUpsQ%3D&spr=https&se=2023-05-06T16%3A00%3A06Z&sp=r",
    "Logo Final (1)": "https://docserverpwaprodsbr.blob.core.windows.net/c155022b-f0d7-44d3-98db-afdc300dd530-1/resource/Assets0Images0512fa82a-f9fe-4aa1-8f10-724d9bc2d14e.png?sv=2018-03-28&sr=b&sig=M82%2FwxEjZYPEgBYhOnsxWCjmPbiZrKYPPwMHNyeBFwg%3D&spr=https&se=2023-05-06T16%3A00%3A06Z&sp=r",
    "ruddy": "https://docserverpwaprodsbr.blob.core.windows.net/c155022b-f0d7-44d3-98db-afdc300dd530-1/resource/Assets0Images052a5ea63-50e0-4e1a-a3e1-addb80e9ef1a.jpeg?sv=2018-03-28&sr=b&sig=Z5eeHAWYmfZnv6M50l0XWykjdrGHvWO4i9MGFBw8eOA%3D&spr=https&se=2023-05-06T16%3A00%3A06Z&sp=r",
    "Walk": "https://docserverpwaprodsbr.blob.core.windows.net/c155022b-f0d7-44d3-98db-afdc300dd530-1/resource/Assets0Images0bb1b3623-66e7-42ea-a982-8cda9e09c291.gif?sv=2018-03-28&sr=b&sig=tJ6QdjJB1rOM5q%2F2SEBkPAmrELHMVe0SNkp2Vz57OKo%3D&spr=https&se=2023-05-06T16%3A00%3A06Z&sp=r"
  },
  "OrderComponentMetadata": {},
  "OrderComponentTemplate": {},
  "OrderDataSource": {
    "colUsuarios": 10,
    "ComboBoxSample": 4,
    "correosColaboradores": 8,
    "CustomGallerySample": 5,
    "datosColaboradores2": 9,
    "DB_Bienestar1": 7,
    "diaFestivoColombia": 11,
    "DropDownSample": 6,
    "Office365Outlook": 2,
    "pdfcl": 3,
    "Permiso": 1,
    "UsuariosdeOffice365": 0
  },
  "OrderGroupControls": {},
  "OrderPcfTemplate": {},
  "OrderTemplate": {},
  "OrderXMLTemplate": {
    "button": 4,
    "checkbox": 8,
    "combobox": 9,
    "datepicker": 5,
    "dropdown": 6,
    "gallery": 3,
    "groupContainer": 0,
    "image": 2,
    "label": 1,
    "rectangle": 10,
    "text": 7
  },
  "OverridablePropertiesEntry": {
    "App": {},
    "ArchivosPdf": {},
    "ArchivosPdfSinSalario": {},
    "Button1": {},
    "Button1_1": {},
    "Button1_2": {},
    "Button1_3": {},
    "Button2": {},
    "Button2_1": {},
    "Button2_2": {},
    "Button2_3": {},
    "Button2_4": {},
    "Button2_5": {},
    "Button2_6": {},
    "Button2_7": {},
    "Button3": {},
    "Button3_1": {},
    "Button3_2": {},
    "Button3_3": {},
    "Button3_4": {},
    "Button5": {},
    "CheckboxSalario": {},
    "colilla": {},
    "ColillaPago": {},
    "ComboBox1": {},
    "ComboBox1_1": {},
    "Container11": {},
    "Container13": {},
    "Container13_1": {},
    "Container13_2": {},
    "Container13_3": {},
    "Container13_4": {},
    "Container13_5": {},
    "Container15": {},
    "Container17": {},
    "Container2": {},
    "Container3": {},
    "Container4": {},
    "Container5": {},
    "Container6": {},
    "Container7": {},
    "Container7_1": {},
    "Container8": {},
    "containerCartaLaboral": {},
    "containerColillas": {},
    "ContainerFormularios": {},
    "containerPermiso": {},
    "containerVacaciones": {},
    "DatePicker4_1": {},
    "DatePicker4_2": {},
    "DatePickerPermiso": {},
    "Gallery3": {},
    "galleryTemplate3": {},
    "HeaderContainer1": {},
    "horaInicialPermiso": {},
    "horaPermisoFinal": {},
    "Host": {},
    "Image1": {},
    "Image1_1": {},
    "Image1_2": {},
    "Image1_3": {},
    "Image10": {},
    "Image11": {},
    "Image7": {},
    "Image8": {},
    "Image9": {},
    "Label1": {},
    "Label10": {},
    "Label11": {},
    "Label11_10": {},
    "Label11_11": {},
    "Label11_3": {},
    "Label11_4": {},
    "Label11_5": {},
    "Label11_6": {},
    "Label11_7": {},
    "Label11_8": {},
    "Label11_9": {},
    "Label12": {},
    "Label12_1": {},
    "Label12_2": {},
    "Label13": {},
    "Label13_1": {},
    "Label13_10": {},
    "Label13_11": {},
    "Label13_12": {},
    "Label13_13": {},
    "Label13_14": {},
    "Label13_15": {},
    "Label13_16": {},
    "Label13_17": {},
    "Label13_18": {},
    "Label13_19": {},
    "Label13_2": {},
    "Label13_20": {},
    "Label13_21": {},
    "Label13_22": {},
    "Label13_23": {},
    "Label13_24": {},
    "Label13_26": {},
    "Label13_27": {},
    "Label13_28": {},
    "Label13_29": {},
    "Label13_3": {},
    "Label13_30": {},
    "Label13_31": {},
    "Label13_32": {},
    "Label13_33": {},
    "Label13_34": {},
    "Label13_4": {},
    "Label13_5": {},
    "Label13_6": {},
    "Label13_7": {},
    "Label13_8": {},
    "Label13_9": {},
    "Label14": {},
    "Label14_1": {},
    "Label14_10": {},
    "Label14_12": {},
    "Label14_13": {},
    "Label14_14": {},
    "Label14_15": {},
    "Label14_17": {},
    "Label14_18": {},
    "Label14_19": {},
    "Label14_2": {},
    "Label14_20": {},
    "Label14_22": {},
    "Label14_25": {},
    "Label14_3": {},
    "Label14_4": {},
    "Label14_5": {},
    "Label14_6": {},
    "Label14_7": {},
    "Label14_9": {},
    "Label15": {},
    "Label15_2": {},
    "Label15_3": {},
    "Label15_4": {},
    "Label15_5": {},
    "Label16": {},
    "Label16_1": {},
    "Label16_2": {},
    "Label17": {},
    "Label17_1": {},
    "Label17_2": {},
    "Label17_3": {},
    "Label17_4": {},
    "Label19": {},
    "Label2": {},
    "Label23": {},
    "Label23_1": {},
    "Label23_2": {},
    "Label24": {},
    "Label24_1": {},
    "Label24_2": {},
    "Label24_3": {},
    "Label24_4": {},
    "Label24_5": {},
    "Label24_7": {},
    "Label28": {},
    "Label28_1": {},
    "Label28_2": {},
    "Label28_3": {},
    "Label28_4": {},
    "Label28_5": {},
    "Label3": {},
    "Label30": {},
    "Label31": {},
    "Label32_1": {},
    "Label4": {},
    "Label5": {},
    "Label5_1": {},
    "Label6": {},
    "Label7": {},
    "Label7_1": {},
    "Label8": {},
    "Label8_1": {},
    "Label8_2": {},
    "Label8_3": {},
    "Label8_4": {},
    "Label8_5": {},
    "Label8_6": {},
    "Label8_7": {},
    "Label8_8": {},
    "Label8_9": {},
    "Label9": {},
    "Label9_1": {},
    "Label9_2": {},
    "Label9_3": {},
    "MainSectionContainer1": {},
    "minutoInicialPermiso": {},
    "minutoPermisoFinal": {},
    "pdfPermisos": {},
    "Rectangle3": {},
    "Rectangle3_1": {},
    "Rectangle3_2": {},
    "Rectangle3_3": {},
    "Screen2": {},
    "ScreenContainer1": {},
    "TextInput1": {},
    "TextInput1_1": {},
    "TextInput1_2": {},
    "TextInput1_3": {},
    "TextInput1_5": {},
    "TextInput1_6": {},
    "TextInput1_7": {},
    "TextInput2": {},
    "TextInput3": {},
    "TextInput3_1": {},
    "TextInput3_2": {},
    "TextInput3_3": {},
    "TextInput4_10": {},
    "TextInput4_11": {},
    "TextInput4_12": {},
    "TextInput4_13": {},
    "TextInput4_14": {},
    "TextInput4_15": {},
    "TextInput4_16": {},
    "TextInput4_17": {},
    "TextInput4_18": {},
    "TextInput4_19": {},
    "TextInput4_20": {},
    "TextInput4_21": {},
    "TextInput4_22": {},
    "TextInput4_23": {},
    "TextInput4_24": {},
    "TextInput4_25": {},
    "TextInput4_26": {},
    "TextInput4_27": {},
    "TextInput4_28": {},
    "TextInput4_6": {},
    "TextInput4_7": {},
    "TextInput4_8": {},
    "TextInput4_9": {},
    "TextInputMotivo": {},
    "Vacaciones": {}
  },
  "PCFDynamicSchemaForIRRetrievalEntry": {},
  "PCFTemplateEntry": {},
  "PublishOrderIndices": {
    "App": 0,
    "ArchivosPdf": 0,
    "ArchivosPdfSinSalario": 0,
    "Button1": 53,
    "Button1_1": 46,
    "Button1_2": 42,
    "Button1_3": 27,
    "Button2": 79,
    "Button2_1": 80,
    "Button2_2": 112,
    "Button2_3": 109,
    "Button2_4": 140,
    "Button2_5": 141,
    "Button2_6": 163,
    "Button2_7": 164,
    "Button3": 54,
    "Button3_1": 85,
    "Button3_2": 116,
    "Button3_3": 145,
    "Button3_4": 228,
    "Button5": 18,
    "CheckboxSalario": 45,
    "colilla": 167,
    "ColillaPago": 0,
    "ComboBox1": 50,
    "ComboBox1_1": 52,
    "Container11": 168,
    "Container13": 177,
    "Container13_1": 178,
    "Container13_2": 196,
    "Container13_3": 201,
    "Container13_4": 222,
    "Container13_5": 193,
    "Container15": 180,
    "Container17": 225,
    "Container2": 9,
    "Container3": 2,
    "Container4": 3,
    "Container5": 4,
    "Container6": 7,
    "Container7": 37,
    "Container7_1": 33,
    "Container8": 10,
    "containerCartaLaboral": 43,
    "containerColillas": 47,
    "ContainerFormularios": 15,
    "containerPermiso": 28,
    "containerVacaciones": 19,
    "DatePicker4_1": 24,
    "DatePicker4_2": 25,
    "DatePickerPermiso": 36,
    "Gallery3": 16,
    "galleryTemplate3": 17,
    "HeaderContainer1": 1,
    "horaInicialPermiso": 38,
    "horaPermisoFinal": 34,
    "Host": 0,
    "Image1": 55,
    "Image1_1": 86,
    "Image1_2": 115,
    "Image1_3": 144,
    "Image10": 169,
    "Image11": 227,
    "Image7": 12,
    "Image8": 13,
    "Image9": 8,
    "Label1": 48,
    "Label10": 26,
    "Label11": 60,
    "Label11_10": 150,
    "Label11_11": 151,
    "Label11_3": 62,
    "Label11_4": 91,
    "Label11_5": 93,
    "Label11_6": 95,
    "Label11_7": 96,
    "Label11_8": 121,
    "Label11_9": 122,
    "Label12": 21,
    "Label12_1": 23,
    "Label12_2": 22,
    "Label13": 67,
    "Label13_1": 65,
    "Label13_10": 98,
    "Label13_11": 99,
    "Label13_12": 101,
    "Label13_13": 103,
    "Label13_14": 106,
    "Label13_15": 108,
    "Label13_16": 125,
    "Label13_17": 110,
    "Label13_18": 113,
    "Label13_19": 114,
    "Label13_2": 69,
    "Label13_20": 77,
    "Label13_21": 131,
    "Label13_22": 139,
    "Label13_23": 154,
    "Label13_24": 156,
    "Label13_26": 162,
    "Label13_27": 158,
    "Label13_28": 134,
    "Label13_29": 135,
    "Label13_3": 71,
    "Label13_30": 127,
    "Label13_31": 138,
    "Label13_32": 130,
    "Label13_33": 133,
    "Label13_34": 159,
    "Label13_4": 70,
    "Label13_5": 74,
    "Label13_6": 78,
    "Label13_7": 81,
    "Label13_8": 83,
    "Label13_9": 84,
    "Label14": 64,
    "Label14_1": 72,
    "Label14_10": 166,
    "Label14_12": 129,
    "Label14_13": 136,
    "Label14_14": 126,
    "Label14_15": 142,
    "Label14_17": 137,
    "Label14_18": 132,
    "Label14_19": 128,
    "Label14_2": 73,
    "Label14_20": 157,
    "Label14_22": 160,
    "Label14_25": 165,
    "Label14_3": 75,
    "Label14_4": 97,
    "Label14_5": 104,
    "Label14_6": 105,
    "Label14_7": 107,
    "Label14_9": 143,
    "Label15": 184,
    "Label15_2": 186,
    "Label15_3": 191,
    "Label15_4": 192,
    "Label15_5": 190,
    "Label16": 66,
    "Label16_1": 76,
    "Label16_2": 100,
    "Label17": 58,
    "Label17_1": 89,
    "Label17_2": 118,
    "Label17_3": 147,
    "Label17_4": 161,
    "Label19": 170,
    "Label2": 44,
    "Label23": 171,
    "Label23_1": 175,
    "Label23_2": 173,
    "Label24": 179,
    "Label24_1": 197,
    "Label24_2": 198,
    "Label24_3": 199,
    "Label24_4": 200,
    "Label24_5": 194,
    "Label24_7": 195,
    "Label28": 181,
    "Label28_1": 183,
    "Label28_2": 182,
    "Label28_3": 188,
    "Label28_4": 187,
    "Label28_5": 189,
    "Label3": 29,
    "Label30": 223,
    "Label31": 224,
    "Label32_1": 226,
    "Label4": 11,
    "Label5": 5,
    "Label5_1": 6,
    "Label6": 20,
    "Label7": 49,
    "Label7_1": 51,
    "Label8": 56,
    "Label8_1": 82,
    "Label8_2": 57,
    "Label8_3": 87,
    "Label8_4": 88,
    "Label8_5": 111,
    "Label8_6": 117,
    "Label8_7": 119,
    "Label8_8": 146,
    "Label8_9": 148,
    "Label9": 30,
    "Label9_1": 31,
    "Label9_2": 32,
    "Label9_3": 40,
    "MainSectionContainer1": 14,
    "minutoInicialPermiso": 39,
    "minutoPermisoFinal": 35,
    "pdfPermisos": 0,
    "Rectangle3": 59,
    "Rectangle3_1": 90,
    "Rectangle3_2": 120,
    "Rectangle3_3": 149,
    "Screen2": 0,
    "ScreenContainer1": 0,
    "TextInput1": 63,
    "TextInput1_1": 94,
    "TextInput1_2": 123,
    "TextInput1_3": 61,
    "TextInput1_5": 92,
    "TextInput1_6": 153,
    "TextInput1_7": 152,
    "TextInput2": 185,
    "TextInput3": 68,
    "TextInput3_1": 102,
    "TextInput3_2": 124,
    "TextInput3_3": 155,
    "TextInput4_10": 203,
    "TextInput4_11": 204,
    "TextInput4_12": 205,
    "TextInput4_13": 206,
    "TextInput4_14": 207,
    "TextInput4_15": 208,
    "TextInput4_16": 209,
    "TextInput4_17": 211,
    "TextInput4_18": 212,
    "TextInput4_19": 213,
    "TextInput4_20": 210,
    "TextInput4_21": 215,
    "TextInput4_22": 216,
    "TextInput4_23": 214,
    "TextInput4_24": 217,
    "TextInput4_25": 220,
    "TextInput4_26": 221,
    "TextInput4_27": 218,
    "TextInput4_28": 219,
    "TextInput4_6": 172,
    "TextInput4_7": 174,
    "TextInput4_8": 176,
    "TextInput4_9": 202,
    "TextInputMotivo": 41,
    "Vacaciones": 0
  },
  "ResourcesJsonIndices": {
    "Image-Fondo App": 1,
    "Image-Logo 2": 3,
    "Image-Logo Final": 2,
    "Image-Logo Final (1)": 5,
    "Image-ruddy": 4,
    "Image-SampleImage": 0,
    "Image-Walk": 7,
    "Pdf-SamplePdf": 6
  },
  "RuleScreenIdWithoutScreen": {},
  "TemplateVersions": {},
  "VolatileProperties": {
    "AnalysisLoadTime": 1.3345331,
    "ControlCount": {
      "button": 18,
      "checkbox": 1,
      "combobox": 2,
      "datepicker": 3,
      "dropdown": 4,
      "gallery": 3,
      "galleryTemplate": 3,
      "groupContainer": 34,
      "icon": 4,
      "image": 12,
      "label": 156,
      "rectangle": 9,
      "screen": 7,
      "text": 80
    },
    "DeserializationLoadTime": 3.2985917
  },
  "WasLocalDatabaseReferencesEmpty": true
}